{
  "name": "compound",
  "Label": "Compound Grid",
  "context": {
    "gridItems": [
      {
        "text": "1"
      },
      {
        "text": "2"
      },
      {
        "text": "3"
      },
      {
        "text": "4"
      },
      {
        "text": "5"
      },
      {
        "text": "6"
      },
      {
        "text": "7"
      },
      {
        "text": "8"
      },
      {
        "text": "9"
      },
      {
        "text": "10"
      },
      {
        "text": "11"
      },
      {
        "text": "12"
      },
      {
        "text": "13"
      },
      {
        "text": "14"
      },
      {
        "text": "15"
      },
      {
        "text": "16"
      },
      {
        "text": "17"
      },
      {
        "text": "18"
      },
      {
        "text": "19"
      },
      {
        "text": "20"
      },
      {
        "text": "21"
      },
      {
        "text": "22"
      },
      {
        "text": "23"
      },
      {
        "text": "24"
      }
    ]
  },
  "variants": [
    {
      "name": "compound23",
      "label": "Compound 2x3 Grid",
      "context": {
        "name": "compound23"
      }
    },
    {
      "name": "compound34",
      "label": "Compound 3x4 Grid",
      "context": {
        "name": "compound34"
      }
    },
    {
      "name": "compound46",
      "label": "Compound 4x6 Grid",
      "context": {
        "name": "compound46"
      }
    }
  ]
}
